megacodist/ErrorHandling.py
megacodist/__init__.py
megacodist/exceptions.py
megacodist/fonts.py
megacodist/html.py
megacodist/keyboard.py
megacodist/singleton.py
megacodist/text.py
megacodist/collections/__init__.py
megacodist/console/__init__.py
megacodist-1.2.0.dist-info/LICENSE
megacodist-1.2.0.dist-info/METADATA
megacodist-1.2.0.dist-info/WHEEL
megacodist-1.2.0.dist-info/top_level.txt
megacodist-1.2.0.dist-info/RECORD
