Metadata-Version: 2.1
Name: megacodist
Version: 1.2.0
Summary: A general library for Python.
Home-page: https://github.com/megacodist/megacodist
Author: Megacodist
Author-email: megacodist@gmail.com
Keywords: list,sorted list
Classifier: Programming Language :: Python :: 3
Classifier: License :: OSI Approved :: MIT License
Classifier: Operating System :: OS Independent
Requires-Python: >=3.10
License-File: LICENSE
